aylien_news_api/__init__.py
aylien_news_api/api_client.py
aylien_news_api/configuration.py
aylien_news_api/exceptions.py
aylien_news_api/rest.py
aylien_news_api/api/__init__.py
aylien_news_api/api/default_api.py
aylien_news_api/models/__init__.py
aylien_news_api/models/aggregated_sentiment.py
aylien_news_api/models/author.py
aylien_news_api/models/autocomplete.py
aylien_news_api/models/autocompletes.py
aylien_news_api/models/category.py
aylien_news_api/models/category_links.py
aylien_news_api/models/category_taxonomy.py
aylien_news_api/models/cluster.py
aylien_news_api/models/clusters.py
aylien_news_api/models/coverages.py
aylien_news_api/models/deprecated_entities.py
aylien_news_api/models/deprecated_entity.py
aylien_news_api/models/deprecated_entity_surface_form.py
aylien_news_api/models/deprecated_related_stories.py
aylien_news_api/models/deprecated_stories.py
aylien_news_api/models/deprecated_story.py
aylien_news_api/models/duns_number.py
aylien_news_api/models/entities.py
aylien_news_api/models/entity.py
aylien_news_api/models/entity_in_text.py
aylien_news_api/models/entity_links.py
aylien_news_api/models/entity_mention.py
aylien_news_api/models/entity_mention_index.py
aylien_news_api/models/entity_sentiment.py
aylien_news_api/models/entity_surface_form.py
aylien_news_api/models/error.py
aylien_news_api/models/error_links.py
aylien_news_api/models/errors.py
aylien_news_api/models/external_ids.py
aylien_news_api/models/histogram_interval.py
aylien_news_api/models/histograms.py
aylien_news_api/models/location.py
aylien_news_api/models/logicals.py
aylien_news_api/models/media.py
aylien_news_api/models/media_format.py
aylien_news_api/models/media_type.py
aylien_news_api/models/nested_entity.py
aylien_news_api/models/parameter.py
aylien_news_api/models/query.py
aylien_news_api/models/rank.py
aylien_news_api/models/rankings.py
aylien_news_api/models/related_stories.py
aylien_news_api/models/representative_story.py
aylien_news_api/models/scope.py
aylien_news_api-5.2.3.dist-info/LICENSE
aylien_news_api-5.2.3.dist-info/METADATA
aylien_news_api-5.2.3.dist-info/WHEEL
aylien_news_api-5.2.3.dist-info/top_level.txt
aylien_news_api-5.2.3.dist-info/RECORD
