Metadata-Version: 1.0
Name: aylien-news-api
Version: 5.2.3
Summary: AYLIEN News API
Home-page: UNKNOWN
Author: API support
Author-email: support@aylien.com
License: UNKNOWN
Keywords: OpenAPI,OpenAPI-Generator,AYLIEN News API
Platform: UNKNOWN
